pymenable/__init__.py
pymenable/builders/__init__.py
pymenable/builders/tableBuilder.py
pymenable/config.py
pymenable/elements/__init__.py
pymenable/elements/baseElements.py
pymenable/elements/inline.py
pymenable/elements/lists.py
pymenable/elements/tables.py
pymenable/openpage.py
pymenable/README.md
pymenable/templates/base.html
pymenable/templates/listOfElements.html
pymenable/THOUGHTS.md
pymenable-0.1.0.dist-info/LICENSE
pymenable-0.1.0.dist-info/WHEEL
pymenable-0.1.0.dist-info/METADATA
pymenable-0.1.0.dist-info/RECORD
