Metadata-Version: 2.1
Name: pymenable
Version: 0.1.0
Summary: Python classes to render accessible HTML elements 
License: MIT
Author: Joel Dodson
Requires-Python: >=3.9,<4.0
Classifier: License :: OSI Approved :: MIT License
Classifier: Programming Language :: Python :: 3
Classifier: Programming Language :: Python :: 3.10
Classifier: Programming Language :: Python :: 3.9
Requires-Dist: Jinja2 (>=3.1.2,<4.0.0)
